{
  "$schema": "https://mintlify.com/docs.json",
  "name": "Click Creators Scraper Server",
  "theme": "aspen",
  "colors": {
    "primary": "#7C3AED",
    "light": "#A78BFA",
    "dark": "#5B21B6"
  },
  "favicon": "/favicon.svg",
  "logo": {
    "light": "/logo/light.svg",
    "dark": "/logo/dark.svg"
  },
  "navbar": {
    "primary": {
      "type": "github",
      "href": "https://github.com/AI-Venture-Studio/Click-Creators-Scraper-Server"
    }
  },
  "footer": {
    "socials": {
      "github": "https://github.com/AI-Venture-Studio/Click-Creators-Scraper-Server"
    }
  },
  "navigation": {
    "tabs": [
      {
        "tab": "Documentation",
        "groups": [
          {
            "group": "Get Started",
            "pages": [
              "introduction",
              "quickstart",
              "architecture"
            ]
          },
          {
            "group": "Installation & Setup",
            "pages": [
              "setup/local-development",
              "setup/environment-variables",
              "setup/database-setup"
            ]
          },
          {
            "group": "Deployment",
            "pages": [
              "deployment/heroku",
              "deployment/render",
              "deployment/scaling"
            ]
          },
          {
            "group": "Guides",
            "pages": [
              "guides/scraping-workflow",
              "guides/job-tracking",
              "guides/batch-processing",
              "guides/multi-platform-support",
              "guides/airtable-integration"
            ]
          },
          {
            "group": "Performance",
            "pages": [
              "performance/optimizations",
              "performance/free-tier-compatibility",
              "performance/monitoring"
            ]
          }
        ]
      },
      {
        "tab": "API Reference",
        "groups": [
          {
            "group": "Async Endpoints",
            "pages": [
              "api/scrape-followers",
              "api/job-status",
              "api/job-results"
            ]
          },
          {
            "group": "Data Ingestion",
            "pages": [
              "api/ingest",
              "api/daily-selection"
            ]
          },
          {
            "group": "Airtable Operations",
            "pages": [
              "api/airtable-sync",
              "api/distribute",
              "api/sync-statuses"
            ]
          },
          {
            "group": "Utilities",
            "pages": [
              "api/health-check",
              "api/run-daily"
            ]
          }
        ]
      },
      {
        "tab": "Advanced",
        "groups": [
          {
            "group": "Workers & Tasks",
            "pages": [
              "advanced/celery-configuration",
              "advanced/task-queues",
              "advanced/worker-management"
            ]
          },
          {
            "group": "Utilities",
            "pages": [
              "advanced/scraper-utils",
              "advanced/gender-detection",
              "advanced/batch-processor"
            ]
          },
          {
            "group": "Troubleshooting",
            "pages": [
              "troubleshooting/common-issues",
              "troubleshooting/debugging",
              "troubleshooting/error-tracking"
            ]
          }
        ]
      }
    ]
  }
}
